Projects_rtl_design/ArithmeticUnit/src/ArithmeticUnit.v
//The Arithmetic Unit 

module Arithmetic_Unit#(parameter OPCODE_L = 8, OPERAND_L = 32, RES_L = 32)(
	input  wire clk,
	input  wire rst, 
	input  wire [OPCODE_L-1 : 0] Opcode,
	input  wire [OPERAND_L-1 : 0] Operand1,
	input  wire [OPERAND_L-1 : 0] Operand2,
	output wire [RES_L-1 : 0] Result);
	
	//Register Declaration
	reg [RES_L-1 :0] res_ff, res_reg;

	
	//Combinational Circuit
	always@(*) begin
		case(Opcode[1:0])
			'b00: begin 
				//Addition
				res_reg = Operand1 + Operand2;
			end 
			'b01: begin 
				//Subtraction
				res_reg = Operand1 - Operand2;
			end 
			'b10: begin 
				//Multplication 
				res_reg = Operand1 * Operand2;
			end 
			'b11: begin 
				//Divison to avoid zero division error
				if( Operand2 != 0) res_reg = Operand1 / Operand2;
				else res_reg = 0;
			end 
			default : begin
				res_reg = 0;
			end 
		endcase
	end 
	
	//Sequential Circuit
	always@(posedge clk) begin
		if(rst) begin 
			res_ff <= 0;
		end else begin 
			res_ff <= res_reg;
		end 
	end 
	
	assign Result = res_ff;
	
endmodule

/*NOTE:
1. For systhesis Optimization in FPGA I use + during addition, - during subtraction 
2. Efficient Div and Mul algorithm must be found 

*/

Projects_rtl_design/ArithmeticUnit/test/test.sv
//Test.sv

module test;
	//PARAMETERS
	localparam OPCODE_L = 2;
	localparam OPERAND_L = 32;
	localparam RES_L = 32;
	localparam TOTAL_OPERATIONS = 4;
	localparam TOTAL_WIDTH = $clog2(TOTAL_OPERATIONS);
	
	//Signal Declaration 
	logic clk;
	logic rst;
	logic [OPCODE_L-1 : 0]  Opcode;
	logic [OPERAND_L-1 : 0] Operand1;
	logic [OPERAND_L-1 : 0] Operand2;
	logic [RES_L-1 : 0]     Result;
	
	
	//DUT instantiation 
	Arithmetic_Unit #(
    	.OPCODE_L(OPCODE_L),
    	.OPERAND_L(OPERAND_L),
    	.RES_L(RES_L)
  	) dut (
    	.clk(clk),
    	.rst(rst),
    	.Opcode(Opcode),
    	.Operand1(Operand1),
    	.Operand2(Operand2),
    	.Result(Result)
  	);
	
	//Testbench Logic 
	always #5 clk = ~clk;
	
	initial begin 
		//Initialize All registers to Zero
		clk = 'b0;
		rst = 'b0;
		Opcode = 'b0;
		Operand1 = 'b0;
		Operand2 = 'b0;
	end 
	
	initial begin 
		//Stimulus - reset
		#10 rst = 1;
		#10 rst = 0;
	end 
	
        initial begin
   	 	$dumpfile("outputd/dump.vcd");
    		$dumpvars(0, test);
  	end

	initial begin 
		//Input Stimulus Logic sending 
		
		//Addition
		#30 
		send_instruction(0, 20, 20);
		#30
		result_check(Result, 40);
		
		//Subtraction
		#30 
		send_instruction(1, 20, 20);
		#30
		result_check(Result, 0);
		
		//Multiplication
		#30 
		send_instruction(2, 20, 20);
		#30
		result_check(Result, 400);
		
		//Divison
		#30 
		send_instruction(3, 20, 20);
		#30
		result_check(Result, 1);		
		
		#50 
		$finish;
	end 
	
	task send_instruction(input [TOTAL_WIDTH-1:0] choice, input [OPERAND_L-1 : 0] Operand_1, input [OPERAND_L-1 : 0] Operand_2);
		//Send input Stimulus
		case(choice)
			'd0: begin 
				Opcode = 'b00;
				Operand1 = Operand_1;
				Operand2 = Operand_2;
			end 
			'd1: begin
				Opcode = 'b01;
				Operand1 = Operand_1;
				Operand2 = Operand_2;
			end 
			'd2: begin
				Opcode = 'b10;
				Operand1 = Operand_1;
				Operand2 = Operand_2;
			end 
			'd3: begin
				Opcode = 'b11;
				Operand1 = Operand_1;
				Operand2 = Operand_2;
			end 
			default: begin
				Opcode = 0;
				Operand1 = 0;
				Operand2 = 0;
			end 
		endcase
	endtask
	
	task result_check(input [RES_L-1 : 0] Res_obtained, input [RES_L-1 : 0] Res_expected);
		//Result Checking Function 
		if(Res_obtained == Res_expected) begin 
			$display("CORRECT!");
		end else begin 
			$display("NOT CORRECT!");
		end 
	endtask 
	
endmodule

Projects_rtl_design/ArithmeticUnit/outputd/dump.vcd
$date
	Thu Jun 12 13:03:18 2025
$end
$version
	Icarus Verilog
$end
$timescale
	1s
$end
$scope module test $end
$var wire 32 ! Result [31:0] $end
$var reg 2 " Opcode [1:0] $end
$var reg 32 # Operand1 [31:0] $end
$var reg 32 $ Operand2 [31:0] $end
$var reg 1 % clk $end
$var reg 1 & rst $end
$scope module dut $end
$var wire 2 ' Opcode [1:0] $end
$var wire 32 ( Operand1 [31:0] $end
$var wire 32 ) Operand2 [31:0] $end
$var wire 32 * Result [31:0] $end
$var wire 1 % clk $end
$var wire 1 & rst $end
$var reg 32 + res_ff [31:0] $end
$var reg 32 , res_reg [31:0] $end
$upscope $end
$scope task result_check $end
$var reg 32 - Res_expected [31:0] $end
$var reg 32 . Res_obtained [31:0] $end
$upscope $end
$scope task send_instruction $end
$var reg 32 / Operand_1 [31:0] $end
$var reg 32 0 Operand_2 [31:0] $end
$var reg 2 1 choice [1:0] $end
$upscope $end
$upscope $end
$enddefinitions $end
#0
$dumpvars
bx 1
bx 0
bx /
bx .
bx -
b0 ,
bx +
bx *
b0 )
b0 (
b0 '
0&
0%
b0 $
b0 #
b0 "
bx !
$end
#5
b0 !
b0 *
b0 +
1%
#10
0%
1&
#15
1%
#20
0%
0&
#25
1%
#30
b101000 ,
0%
b10100 $
b10100 )
b10100 #
b10100 (
b10100 0
b10100 /
b0 1
#35
b101000 !
b101000 *
b101000 +
1%
#40
0%
#45
1%
#50
0%
#55
1%
#60
0%
b101000 -
b101000 .
#65
1%
#70
0%
#75
1%
#80
0%
#85
1%
#90
b0 ,
0%
b1 "
b1 '
b1 1
#95
b0 !
b0 *
b0 +
1%
#100
0%
#105
1%
#110
0%
#115
1%
#120
0%
b0 -
b0 .
#125
1%
#130
0%
#135
1%
#140
0%
#145
1%
#150
b110010000 ,
0%
b10 "
b10 '
b10 1
#155
b110010000 !
b110010000 *
b110010000 +
1%
#160
0%
#165
1%
#170
0%
#175
1%
#180
0%
b110010000 -
b110010000 .
#185
1%
#190
0%
#195
1%
#200
0%
#205
1%
#210
b1 ,
0%
b11 "
b11 '
b11 1
#215
b1 !
b1 *
b1 +
1%
#220
0%
#225
1%
#230
0%
#235
1%
#240
0%
b1 -
b1 .
